aimglyze/__init__.py
aimglyze/analyzer.py
aimglyze/cli.py
aimglyze/gui.py
aimglyze/server.py
aimglyze/apps/App-DescTags/config.yaml
aimglyze/apps/App-DescTags/sample-msg.json
aimglyze/apps/App-DescTags/frontend/app.js
aimglyze/apps/App-DescTags/frontend/favicon.ico
aimglyze/apps/App-DescTags/frontend/index.html
aimglyze/apps/App-DescTags/frontend/style.css
aimglyze/apps/App-TaskScore/config.yaml
aimglyze/apps/App-TaskScore/sample-msg.json
aimglyze/apps/App-TaskScore/frontend/app.js
aimglyze/apps/App-TaskScore/frontend/chart-v3.9.1.min.js
aimglyze/apps/App-TaskScore/frontend/index.html
aimglyze/apps/App-TaskScore/frontend/style.css
aimglyze/logos/aimglyze-light-256x256.png
aimglyze/logos/aimglyze-light.ico
aimglyze-0.2.4.dist-info/licenses/LICENSE
aimglyze-0.2.4.dist-info/METADATA
aimglyze-0.2.4.dist-info/WHEEL
aimglyze-0.2.4.dist-info/entry_points.txt
aimglyze-0.2.4.dist-info/top_level.txt
aimglyze-0.2.4.dist-info/RECORD
