Metadata-Version: 2.4
Name: aimglyze
Version: 0.2.4
Summary: AI图片分析器，支持多模型（DeepSeek, Gemini, ZhipuAI等）
Home-page: https://github.com/shmilee/aimglyze
Author: shmilee
Author-email: shmilee.zju@gmail.com
License: MIT
Project-URL: Bug Reports, https://github.com/shmilee/aimglyze/issues
Project-URL: Source, https://github.com/shmilee/aimglyze
Keywords: ai,image-analysis,deepseek,gemini,zhipuai,multimodal
Classifier: Programming Language :: Python :: 3
Classifier: Programming Language :: Python :: 3.10
Classifier: Programming Language :: Python :: 3.11
Classifier: Programming Language :: Python :: 3.12
Classifier: Programming Language :: Python :: 3.13
Classifier: Operating System :: OS Independent
Classifier: Topic :: Scientific/Engineering :: Artificial Intelligence
Classifier: Topic :: Multimedia :: Graphics
Classifier: Intended Audience :: Developers
Requires-Python: >=3.10
License-File: LICENSE
Requires-Dist: pyyaml>=6.0
Requires-Dist: json-repair>=0.54.0
Requires-Dist: openai>=1.0.0
Requires-Dist: zai-sdk>=0.1.0
Provides-Extra: full
Requires-Dist: google-genai>=0.3.0; extra == "full"
Dynamic: author
Dynamic: author-email
Dynamic: classifier
Dynamic: description
Dynamic: description-content-type
Dynamic: home-page
Dynamic: keywords
Dynamic: license
Dynamic: license-file
Dynamic: project-url
Dynamic: provides-extra
Dynamic: requires-dist
Dynamic: requires-python
Dynamic: summary
